subscleaner/__init__.py
subscleaner/subscleaner.py
subscleaner-2.1.5.dist-info/METADATA
subscleaner-2.1.5.dist-info/WHEEL
subscleaner-2.1.5.dist-info/entry_points.txt
subscleaner-2.1.5.dist-info/licenses/LICENSE
subscleaner-2.1.5.dist-info/RECORD
