Metadata-Version: 2.4
Name: subscleaner
Version: 2.1.5
Summary: Remove advertisements from subtitle files
Project-URL: Homepage, https://gitlab.com/rogs/subscleaner/
Project-URL: Repository, https://gitlab.com/rogs/subscleaner/
Project-URL: Documentation, https://gitlab.com/rogs/subscleaner/-/blob/master/README.md
Author-email: Roger Gonzalez <roger@rogs.me>
License: GPL-3.0-or-later
License-File: LICENSE
Keywords: subs,subtitles
Classifier: License :: OSI Approved :: GNU General Public License v3 or later (GPLv3+)
Classifier: Operating System :: OS Independent
Classifier: Programming Language :: Python :: 3
Requires-Python: >=3.9
Requires-Dist: appdirs>=1.4.4
Requires-Dist: chardet>=5.2.0
Requires-Dist: pysrt>=1.1.2
